MovieTVVis/MTVFilter.py
MovieTVVis/MovieTVVis.py
MovieTVVis/__init__.py
MovieTVVis/dash_app.py
MovieTVVis/helper.py
NorwayTop10/NorwayTop10.py
NorwayTop10/__init__.py
Scraper/Scraper.py
Scraper/__init__.py
digiscreens_uib-1.2.dist-info/METADATA
digiscreens_uib-1.2.dist-info/WHEEL
digiscreens_uib-1.2.dist-info/top_level.txt
digiscreens_uib-1.2.dist-info/RECORD
