Metadata-Version: 2.1
Name: digiscreens-uib
Version: 1.2
Summary: Digiscreens package
Home-page: https://git.app.uib.no/ii/inf219/23h/digiscreens
Author: Digiscreens_team_uib
License: MIT
Requires-Dist: numpy
Requires-Dist: pandas
Requires-Dist: plotly
